ecies_xmr/__init__.py
ecies_xmr/ecies.py
ecies_xmr/ed25519.py
ecies_xmr-0.2.dist-info/LICENSE
ecies_xmr-0.2.dist-info/METADATA
ecies_xmr-0.2.dist-info/WHEEL
ecies_xmr-0.2.dist-info/top_level.txt
ecies_xmr-0.2.dist-info/RECORD
