Metadata-Version: 2.1
Name: ecies_xmr
Version: 0.2
Summary: ECIES implementation for the Monero Edwards25519 curve
Home-page: https://github.com/mewmix/ecies-xmr
Author: Alexander Klein
Author-email: alexanderjamesklein@gmail.com
Requires-Python: >=3.6
License-File: LICENSE
Requires-Dist: pycryptodome
